README.rst
setup.py
bin/chronograph
chronograph/__init__.py
chronograph/admin.py
chronograph/models.py
chronograph/settings.py
chronograph/views.py
chronograph/compatibility/__init__.py
chronograph/compatibility/dates.py
chronograph/fixtures/test_jobs.json
chronograph/management/__init__.py
chronograph/management/commands/__init__.py
chronograph/management/commands/cron.py
chronograph/management/commands/cron_clean.py
chronograph/management/commands/cron_serial.py
chronograph/management/commands/cronserver.py
chronograph/management/commands/run_job.py
chronograph/templates/chronograph/error_message.txt
chronograph/templatetags/__init__.py
chronograph/templatetags/chronograph_tags.py
chronograph/tests/__init__.py
chronograph/tests/commands.py
ispm_django_chronograph.egg-info/PKG-INFO
ispm_django_chronograph.egg-info/SOURCES.txt
ispm_django_chronograph.egg-info/dependency_links.txt
ispm_django_chronograph.egg-info/not-zip-safe
ispm_django_chronograph.egg-info/requires.txt
ispm_django_chronograph.egg-info/top_level.txt