Metadata-Version: 1.1
Name: ispm-django-chronograph
Version: 0.3.3.1
Summary: A fork of https://pypi.python.org/pypi/django-chronograph
Home-page: https://github.com/marcio0/ispm-django-chronograph
Author: marcio0
Author-email: marc.cr@gmail.com
License: BSD
Platform: UNKNOWN
Classifier: Environment :: Web Environment
Classifier: Intended Audience :: Developers
Classifier: License :: OSI Approved :: BSD License
Classifier: Operating System :: OS Independent
Classifier: Programming Language :: Python
Classifier: Framework :: Django
